{"Model: mango": {"content": "", "subsections": {"AssociatedMangoObject": {"content": ""}, "BitField": {"content": ""}, "Brightness": {"content": ""}, "Color": {"content": ""}, "ColorDef": {"content": ""}, "DataLink": {"content": ""}, "EpochPosition": {"content": ""}, "EpochPositionCorrelations": {"content": ""}, "EpochPositionErrors": {"content": ""}, "Label": {"content": ""}, "MangoObject": {"content": ""}, "PhotometricProperty": {"content": ""}, "PhysicalProperty": {"content": ""}, "Property": {"content": ""}, "Shape": {"content": ""}, "Status": {"content": ""}, "StatusValue": {"content": ""}, "StatusValues": {"content": ""}, "VocabularyTerm": {"content": ""}, "ShapeSerialization": {"content": ""}, "ColorDefinition": {"content": ""}}}, "Package: error": {"content": "", "subsections": {"Asymmetric1D": {"content": ""}, "Ellipse": {"content": ""}, "ErrorCorrMatrix": {"content": ""}, "ErrorCovMatrix": {"content": ""}, "PropertyError (Abstract)": {"content": ""}, "Symmetric1D": {"content": ""}}}, "Package: dataorigin": {"content": "", "subsections": {"Article": {"content": ""}, "DataOrigin": {"content": ""}, "License": {"content": ""}, "QueryOrigin": {"content": ""}}}}